Metadata-Version: 1.1
Name: SequencerBot
Version: 0.0.1
Summary: Telegram sequence chat bot verifier
Home-page: https://github.com/bocajnotnef/telegram-sequence-bot
Author: Jake Fenton
Author-email: jake@fenton.io
License: MIT License
Download-URL: https://github.com/bocajnotnef/telegram-sequence-bot/0.0.1.tar.gz
Keywords: bot,telegram
Platform: UNKNOWN
Classifier: Development Status :: 2 - Pre-Alpha
Classifier: Intended Audience :: Developers
Classifier: License :: OSI Approved :: MIT License
Classifier: Operating System :: Unix
Classifier: Operating System :: POSIX
Classifier: Programming Language :: Python :: 3.6
Classifier: Topic :: Utilities
